retrieve_texts_from_dwgs/__init__.py
retrieve_texts_from_dwgs/retrieve_texts_from_dwgs.py
xgh_retrieve_texts_from_dwgs-0.0.0.dist-info/METADATA
xgh_retrieve_texts_from_dwgs-0.0.0.dist-info/WHEEL
xgh_retrieve_texts_from_dwgs-0.0.0.dist-info/entry_points.txt
xgh_retrieve_texts_from_dwgs-0.0.0.dist-info/top_level.txt
xgh_retrieve_texts_from_dwgs-0.0.0.dist-info/RECORD
