Metadata-Version: 2.1
Name: xgh-retrieve-texts-from-dwgs
Version: 0.0.0
Summary: # retrieve_texts_from_dwgs 从钻孔柱状图中提取钻孔信息，写入到：  - Field Geological Descriptions.csv ： Location ID,Depth Top,Depth Base,Legend Code,Geology Code,Geology Code 2,BGS Lexicon,Description - Location Details.csv  ：Location ID,Location Type,Easting,Northing,Ground Level,Final Depth
Home-page: UNKNOWN
License: UNKNOWN
Platform: UNKNOWN
